solace_ai_connector_web/.env.sample
solace_ai_connector_web/__init__.py
solace_ai_connector_web/backend/__init__.py
solace_ai_connector_web/backend/requirements.txt
solace_ai_connector_web/backend/server.py
solace_ai_connector_web/backend/server_base.py
solace_ai_connector_web/frontend/static/client/favicon.ico
solace_ai_connector_web/frontend/static/client/index.html
solace_ai_connector_web/frontend/static/client/solace_chat_header_icon.png
solace_ai_connector_web/frontend/static/client/solace_chat_icon.png
solace_ai_connector_web/frontend/static/client/solace_chat_icon_raw.png
solace_ai_connector_web/frontend/static/client/assets/ConfigProvider-Du21v841.js
solace_ai_connector_web/frontend/static/client/assets/_index-f_JOBitK.js
solace_ai_connector_web/frontend/static/client/assets/auth-callback-Dz_eWSM9.js
solace_ai_connector_web/frontend/static/client/assets/components-CZgPMZIv.js
solace_ai_connector_web/frontend/static/client/assets/entry.client-Dx10338k.js
solace_ai_connector_web/frontend/static/client/assets/index-5y0-HiVp.js
solace_ai_connector_web/frontend/static/client/assets/jsx-runtime-CNvHvvCs.js
solace_ai_connector_web/frontend/static/client/assets/manifest-797d6555.js
solace_ai_connector_web/frontend/static/client/assets/root-DYs-ZjeE.css
solace_ai_connector_web/frontend/static/client/assets/root-V1rT3Np0.js
solace_ai_connector_web-0.2.2.dist-info/METADATA
solace_ai_connector_web-0.2.2.dist-info/WHEEL
solace_ai_connector_web-0.2.2.dist-info/entry_points.txt
solace_ai_connector_web-0.2.2.dist-info/licenses/LICENSE
solace_ai_connector_web-0.2.2.dist-info/RECORD
