Metadata-Version: 2.4
Name: solace-ai-connector-web
Version: 0.2.2
Summary: Web interface for Solace Agent Mesh
Author-email: Edward Funnekotter <edward.funnekotter@solace.com>
License: MIT License
License-File: LICENSE
Classifier: Programming Language :: Python
Classifier: Programming Language :: Python :: 3.10
Classifier: Programming Language :: Python :: 3.11
Classifier: Programming Language :: Python :: 3.12
Classifier: Programming Language :: Python :: 3.13
Classifier: Programming Language :: Python :: Implementation :: CPython
Classifier: Programming Language :: Python :: Implementation :: PyPy
Requires-Python: >=3.10.16
Requires-Dist: flask-cors~=5.0.0
Requires-Dist: flask-wtf~=1.2.2
Requires-Dist: flask~=3.0.3
Requires-Dist: python-dotenv~=1.0.1
Requires-Dist: requests~=2.32.3
